scanpatterns/__init__.py
scanpatterns/__version__.py
scanpatterns/patterns.py
scanpatterns-0.2.0.dist-info/METADATA
scanpatterns-0.2.0.dist-info/WHEEL
scanpatterns-0.2.0.dist-info/top_level.txt
scanpatterns-0.2.0.dist-info/RECORD
