Metadata-Version: 2.1
Name: scanpatterns
Version: 0.2.0
Summary: Parametric patterns for laser scanning microscopy
Home-page: https://github.com/sstucker/pyscanpatterns
Author-email: sstucker@bu.edu
License: GPLv3
Platform: UNKNOWN
Classifier: License :: OSI Approved :: MIT License
Classifier: Programming Language :: Python
Classifier: Programming Language :: Python :: 3
Classifier: Programming Language :: Python :: 3.6
Classifier: Programming Language :: Python :: Implementation :: CPython
Classifier: Programming Language :: Python :: Implementation :: PyPy
Requires-Python: >=3.6.0
Requires-Dist: numpy
Requires-Dist: setuptools
Requires-Dist: pip
